excelalchemy/__init__.py
excelalchemy/const.py
excelalchemy/exc.py
excelalchemy/py.typed
excelalchemy/core/__init__.py
excelalchemy/core/abstract.py
excelalchemy/core/alchemy.py
excelalchemy/core/writer.py
excelalchemy/helper/__init__.py
excelalchemy/helper/pydantic.py
excelalchemy/types/__init__.py
excelalchemy/types/abstract.py
excelalchemy/types/alchemy.py
excelalchemy/types/field.py
excelalchemy/types/header.py
excelalchemy/types/identity.py
excelalchemy/types/result.py
excelalchemy/types/value/__init__.py
excelalchemy/types/value/boolean.py
excelalchemy/types/value/date.py
excelalchemy/types/value/date_range.py
excelalchemy/types/value/email.py
excelalchemy/types/value/money.py
excelalchemy/types/value/multi_checkbox.py
excelalchemy/types/value/number.py
excelalchemy/types/value/number_range.py
excelalchemy/types/value/organization.py
excelalchemy/types/value/phone_number.py
excelalchemy/types/value/radio.py
excelalchemy/types/value/staff.py
excelalchemy/types/value/string.py
excelalchemy/types/value/tree.py
excelalchemy/types/value/url.py
excelalchemy/util/__init__.py
excelalchemy/util/convertor.py
excelalchemy/util/file.py
excelalchemy-1.1.0.dist-info/LICENSE
excelalchemy-1.1.0.dist-info/WHEEL
excelalchemy-1.1.0.dist-info/METADATA
excelalchemy-1.1.0.dist-info/RECORD
