Metadata-Version: 2.1
Name: ExcelAlchemy
Version: 1.1.0
Summary: A Python Library for Reading and Writing Excel Files
Author-email: 何睿 <hrui835@gmail.com>
Requires-Python: >=3.10
Classifier: License :: OSI Approved :: MIT License
Requires-Dist: pandas >=2.0.0, <2.1.0
Requires-Dist: minio >=7.0.0, <8
Requires-Dist: pydantic[email] >=1.9, <2
Requires-Dist: openpyxl >=3.0.10, <4
Requires-Dist: pendulum >=2.1.2, <3
Requires-Dist: pandas-stubs ; extra == "development"
Requires-Dist: black ; extra == "development"
Requires-Dist: isort ; extra == "development"
Requires-Dist: mypy ; extra == "development"
Requires-Dist: pylint ; extra == "development"
Requires-Dist: pre-commit ; extra == "development"
Requires-Dist: pyright==1.1.299 ; extra == "development"
Requires-Dist: pytest ; extra == "development"
Requires-Dist: coverage ; extra == "development"
Requires-Dist: pytest-cov ; extra == "development"
Project-URL: Home, https://github.com/SundayWindy/excelalchemy
Provides-Extra: development
